get_local_address.py
get_local_address-0.1.0a0.dist-info/licenses/LICENSE
get_local_address-0.1.0a0.dist-info/METADATA
get_local_address-0.1.0a0.dist-info/WHEEL
get_local_address-0.1.0a0.dist-info/top_level.txt
get_local_address-0.1.0a0.dist-info/RECORD
