Metadata-Version: 2.4
Name: get-local-address
Version: 0.1.0a0
Summary: A simple utility to determine the local IP address that would be used to communicate with a specified remote UDP server.
Author-email: Jifeng Wu <jifengwu2k@gmail.com>
License-Expression: MIT
Project-URL: Homepage, https://github.com/jifengwu2k/get-local-address
Project-URL: Bug Tracker, https://github.com/jifengwu2k/get-local-address/issues
Classifier: Programming Language :: Python :: 2
Classifier: Programming Language :: Python :: 3
Classifier: Operating System :: OS Independent
Requires-Python: >=2
License-File: LICENSE
Dynamic: license-file
